cubyc/__init__.py
cubyc/cli.py
cubyc/query/__init__.py
cubyc/query/query.py
cubyc/query/query_engine/__init__.py
cubyc/query/query_engine/local_query_engine.py
cubyc/query/query_engine/query_engine.py
cubyc/query/query_engine/remote_query_engine/__init__.py
cubyc/query/query_engine/remote_query_engine/bitbucket_query_engine.py
cubyc/query/query_engine/remote_query_engine/github_query_engine.py
cubyc/query/query_engine/remote_query_engine/gitlab_query_engine.py
cubyc/query/query_engine/remote_query_engine/remote_query_engine.py
cubyc/run.py
cubyc/templates/__init__.py
cubyc/templates/gitignore_template
cubyc/utils.py
cubyc-0.1.2.dist-info/LICENSE
cubyc-0.1.2.dist-info/METADATA
cubyc-0.1.2.dist-info/WHEEL
cubyc-0.1.2.dist-info/entry_points.txt
cubyc-0.1.2.dist-info/RECORD
