Metadata-Version: 2.1
Name: cubyc
Version: 0.1.2
Summary: The repository for all your experiments
Home-page: https://github.com/cubyc-dev/cubyc
License: LGPL-3.0
Author: Esteban Safranchik
Author-email: esteban@cubyc.com
Requires-Python: >=3.8
Classifier: Intended Audience :: Developers
Classifier: Intended Audience :: Science/Research
Classifier: License :: OSI Approved :: GNU Lesser General Public License v3 (LGPLv3)
Classifier: Programming Language :: Python :: 3
Classifier: Programming Language :: Python :: 3.8
Classifier: Programming Language :: Python :: 3.9
Classifier: Programming Language :: Python :: 3.10
Classifier: Programming Language :: Python :: 3.11
Classifier: Programming Language :: Python :: 3.12
Classifier: Programming Language :: SQL
Requires-Dist: aiohttp (>=3.9.5)
Requires-Dist: duckdb (>=0.8.0) ; python_version < "3.12"
Requires-Dist: duckdb (>=1.0.0) ; python_version >= "3.12"
Requires-Dist: fasteners (>=0.19)
Requires-Dist: gitpython (>=3.1.43)
Requires-Dist: ijson (>=3.2.3)
Requires-Dist: ipython (>=7.31.1)
Requires-Dist: keyring (>=25.2.1)
Requires-Dist: numpy (>=1.3.0) ; python_version < "3.12"
Requires-Dist: numpy (>=2.0.0) ; python_version >= "3.12"
Requires-Dist: pandas (>=2.0.0)
Requires-Dist: psutil (>=5.9.8)
Requires-Dist: pydantic (>=2.7.1)
Requires-Dist: pyyaml (>=6.0.1)
Requires-Dist: rich (>=12.4.0)
Requires-Dist: tabulate (>=0.9.0)
Requires-Dist: typer (>=0.12.0)
Requires-Dist: wonderwords (>=2.2.0)
Project-URL: Documentation, https://docs.cubyc.com
Project-URL: Repository, https://github.com/cubyc-dev/cubyc
